{
  "id": 155,
  "created_at": "2016-10-27T16:37:44+00:00",
  "updated_at": "2017-04-14T17:20:02.756+00:00",
  "title": "Cross Site Scripting",
  "author": "Jim O'Brien",
  "module_name": "sanitize-html",
  "publish_date": "2017-04-14T17:20:02.755+00:00",
  "cves": [],
  "vulnerable_versions": "<=1.2.2",
  "patched_versions": ">=1.2.3",
  "slug": "sanitize-html_cross-site-scripting",
  "overview": "sanitize-html is a library for scrubbing html input for malicious values\nVersions 1.2.2 and below have a cross site scripting vulnerability under certain scenarios:\n\nEntering the following:\n\n`<IMG SRC= onmouseover=\"alert('XSS');\">`\nproduces the following:\n\n`<img src=\"onmouseover=\"alert('XSS');\"\" />`\nThis is definitely invalid HTML, but would suggest that it's being interpreted incorrectly by the parser.",
  "recommendation": "Upgrade to version 1.2.3 or later.",
  "references": "* https://github.com/punkave/sanitize-html/issues/19\n* https://github.com/punkave/sanitize-html/pull/20",
  "cvss_vector": "CVSS:3.0/AV:N/AC:L/PR:N/UI:R/S:U/C:L/I:L/A:N",
  "cvss_score": 5.4,
  "coordinating_vendor": "^Lift Security"
}